{
  "id": "112372591307545398",
  "uri": "https://mastodonapp.uk/users/adaddinsane/statuses/112372591281273501",
  "url": "https://mastodonapp.uk/@adaddinsane/112372591281273501",
  "account": {
    "id": "109319830044901513",
    "username": "adaddinsane",
    "acct": "adaddinsane@mastodonapp.uk",
    "display_name": "adaddinsane (Steve Turnbull)",
    "locked": false,
    "created_at": "2022-11-09T00:00:00Z",
    "followers_count": 640,
    "following_count": 558,
    "statuses_count": 6264,
    "note": "\u003cp\u003ePutting words together in pleasing ways.\u003c/p\u003e\u003cp\u003eDiscover my Fantasy, SF and Steampunk books, also erotica, with LGBTQ+ and diverse leads. \u003c/p\u003e\u003cp\u003ePatterner's World best reading order:\u003c/p\u003e\u003cp\u003e * Dragons of Esternes (4 books, complete)\u003cbr\u003e * Patterner's Path (4 books, complete)\u003cbr\u003e * Dragons of a Wounded Land (5 books, not complete)\u003c/p\u003e\u003cp\u003eI have no time for bigots (of any stripe). Safe for everyone else.\u003c/p\u003e\u003cp\u003e\u003ca href=\"https://mastodonapp.uk/tags/Writing\" class=\"mention hashtag\" rel=\"nofollow noopener\" target=\"_blank\"\u003e#\u003cspan\u003eWriting\u003c/span\u003e\u003c/a\u003e \u003ca href=\"https://mastodonapp.uk/tags/WriteOnce\" class=\"mention hashtag\" rel=\"nofollow noopener\" target=\"_blank\"\u003e#\u003cspan\u003eWriteOnce\u003c/span\u003e\u003c/a\u003e \u003ca href=\"https://mastodonapp.uk/tags/WritingCommunity\" class=\"mention hashtag\" rel=\"nofollow noopener\" target=\"_blank\"\u003e#\u003cspan\u003eWritingCommunity\u003c/span\u003e\u003c/a\u003e \u003ca href=\"https://mastodonapp.uk/tags/Fantasy\" class=\"mention hashtag\" rel=\"nofollow noopener\" target=\"_blank\"\u003e#\u003cspan\u003eFantasy\u003c/span\u003e\u003c/a\u003e \u003ca href=\"https://mastodonapp.uk/tags/SciFi\" class=\"mention hashtag\" rel=\"nofollow noopener\" target=\"_blank\"\u003e#\u003cspan\u003eSciFi\u003c/span\u003e\u003c/a\u003e \u003ca href=\"https://mastodonapp.uk/tags/Steampunk\" class=\"mention hashtag\" rel=\"nofollow noopener\" target=\"_blank\"\u003e#\u003cspan\u003eSteampunk\u003c/span\u003e\u003c/a\u003e \u003ca href=\"https://mastodonapp.uk/tags/Erotica\" class=\"mention hashtag\" rel=\"nofollow noopener\" target=\"_blank\"\u003e#\u003cspan\u003eErotica\u003c/span\u003e\u003c/a\u003e \u003ca href=\"https://mastodonapp.uk/tags/Queer\" class=\"mention hashtag\" rel=\"nofollow noopener\" target=\"_blank\"\u003e#\u003cspan\u003eQueer\u003c/span\u003e\u003c/a\u003e \u003ca href=\"https://mastodonapp.uk/tags/biFic\" class=\"mention hashtag\" rel=\"nofollow noopener\" target=\"_blank\"\u003e#\u003cspan\u003ebiFic\u003c/span\u003e\u003c/a\u003e \u003ca href=\"https://mastodonapp.uk/tags/3dRender\" class=\"mention hashtag\" rel=\"nofollow noopener\" target=\"_blank\"\u003e#\u003cspan\u003e3dRender\u003c/span\u003e\u003c/a\u003e \u003ca href=\"https://mastodonapp.uk/tags/3d\" class=\"mention hashtag\" rel=\"nofollow noopener\" target=\"_blank\"\u003e#\u003cspan\u003e3d\u003c/span\u003e\u003c/a\u003e \u003ca href=\"https://mastodonapp.uk/tags/DazStudio\" class=\"mention hashtag\" rel=\"nofollow noopener\" target=\"_blank\"\u003e#\u003cspan\u003eDazStudio\u003c/span\u003e\u003c/a\u003e\u003c/p\u003e",
    "url": "https://mastodonapp.uk/@adaddinsane",
    "avatar": "https://media.infosec.exchange/infosec.exchange/cache/accounts/avatars/109/319/830/044/901/513/original/056155f97b596dbc.png",
    "avatar_static": "https://media.infosec.exchange/infosec.exchange/cache/accounts/avatars/109/319/830/044/901/513/original/056155f97b596dbc.png",
    "header": "https://media.infosec.exchange/infosec.exchange/cache/accounts/headers/109/319/830/044/901/513/original/2791bddbb210879b.jpg",
    "header_static": "https://media.infosec.exchange/infosec.exchange/cache/accounts/headers/109/319/830/044/901/513/original/2791bddbb210879b.jpg",
    "emojis": [],
    "moved": null,
    "fields": [
      {
        "name": "My books",
        "value": "\u003ca href=\"https://taupress.com/books\" rel=\"nofollow noopener\" translate=\"no\" target=\"_blank\"\u003e\u003cspan class=\"invisible\"\u003ehttps://\u003c/span\u003e\u003cspan class=\"\"\u003etaupress.com/books\u003c/span\u003e\u003cspan class=\"invisible\"\u003e\u003c/span\u003e\u003c/a\u003e",
        "verified_at": "0001-01-01T00:00:00Z"
      },
      {
        "name": "Stuff",
        "value": "cis bi 🌈 | he/him | LGBTQ+",
        "verified_at": "0001-01-01T00:00:00Z"
      },
      {
        "name": "Medium",
        "value": "\u003ca href=\"https://medium.com/@adaddinsane\" rel=\"nofollow noopener\" translate=\"no\" target=\"_blank\"\u003e\u003cspan class=\"invisible\"\u003ehttps://\u003c/span\u003e\u003cspan class=\"\"\u003emedium.com/@adaddinsane\u003c/span\u003e\u003cspan class=\"invisible\"\u003e\u003c/span\u003e\u003c/a\u003e",
        "verified_at": "0001-01-01T00:00:00Z"
      },
      {
        "name": "My 3D renders",
        "value": "\u003ca href=\"https://pixelfed.scot/@adaddinsane\" rel=\"nofollow noopener\" translate=\"no\" target=\"_blank\"\u003e\u003cspan class=\"invisible\"\u003ehttps://\u003c/span\u003e\u003cspan class=\"\"\u003epixelfed.scot/@adaddinsane\u003c/span\u003e\u003cspan class=\"invisible\"\u003e\u003c/span\u003e\u003c/a\u003e",
        "verified_at": "0001-01-01T00:00:00Z"
      }
    ],
    "bot": false,
    "discoverable": true,
    "source": null,
    "followed_tags": null
  },
  "in_reply_to_id": "112372242894383612",
  "in_reply_to_account_id": "109300069582362316",
  "reblog": null,
  "content": "\u003cp\u003e\u003cspan class=\"h-card\" translate=\"no\"\u003e\u003ca href=\"https://infosec.exchange/@sudorandom\" class=\"u-url mention\" rel=\"nofollow noopener\" target=\"_blank\"\u003e@\u003cspan\u003esudorandom\u003c/span\u003e\u003c/a\u003e\u003c/span\u003e\u003c/p\u003e\u003cp\u003eNo, I just sit down and start.\u003c/p\u003e",
  "created_at": "2024-05-02T17:07:46Z",
  "edited_at": "0001-01-01T00:00:00Z",
  "emojis": [],
  "replies_count": 1,
  "reblogs_count": 0,
  "favourites_count": 0,
  "reblogged": false,
  "favourited": false,
  "bookmarked": false,
  "muted": false,
  "sensitive": false,
  "spoiler_text": "",
  "visibility": "public",
  "media_attachments": [],
  "mentions": [
    {
      "url": "https://infosec.exchange/@sudorandom",
      "username": "sudorandom",
      "acct": "sudorandom",
      "id": "109300069582362316"
    }
  ],
  "tags": [],
  "card": null,
  "poll": null,
  "application": {
    "id": "",
    "redirect_uri": "",
    "client_id": "",
    "client_secret": ""
  },
  "language": "en",
  "pinned": null,
  "params": {
    "application_id": "",
    "idempotency": "",
    "in_reply_to_id": null,
    "media_ids": null,
    "poll": null,
    "sensitive": false,
    "spoiler_text": "",
    "text": "",
    "visibility": ""
  }
}